pypistats/__init__.py
pypistats/__main__.py
pypistats/_cache.py
pypistats/_version.py
pypistats/cli.py
pypistats-1.13.0.dist-info/METADATA
pypistats-1.13.0.dist-info/WHEEL
pypistats-1.13.0.dist-info/entry_points.txt
pypistats-1.13.0.dist-info/licenses/LICENSE.txt
pypistats-1.13.0.dist-info/RECORD
